quizlearnpackage/__init__.py
quizlearnpackage/__main__.py
quizlearnpackage/quizlearn.py
quizlearnpackage-0.1.6.dist-info/licenses/LICENSE
quizlearnpackage-0.1.6.dist-info/METADATA
quizlearnpackage-0.1.6.dist-info/WHEEL
quizlearnpackage-0.1.6.dist-info/entry_points.txt
quizlearnpackage-0.1.6.dist-info/top_level.txt
quizlearnpackage-0.1.6.dist-info/RECORD
