Metadata-Version: 2.4
Name: quizlearnpackage
Version: 0.1.6
Summary: Python package that allows the user to play four different academic games which aim to improve the player's abilities in four different subjects. Developed with pipenv, built with build using setuptools, uploaded to PyPI using twine, and distributed via pip.
Author-email: Tim Xu <tzx201@nyu.edu>, Anna Ye <azy2006@nyu.edu>, Jack Wang <jjw9077@nyu.edu>, Joylyn Gong <jxg2306@nyu.edu>
License:                     GNU GENERAL PUBLIC LICENSE
Keywords: python,package,build,tutorial
Classifier: Programming Language :: Python :: 3
Classifier: Intended Audience :: Education
Classifier: License :: OSI Approved :: GNU General Public License v3 (GPLv3)
Classifier: Operating System :: OS Independent
Requires-Python: >=3.9
License-File: LICENSE
Provides-Extra: dev
Requires-Dist: pytest; extra == "dev"
Dynamic: license-file
